{
  "_설명": "와와 유튜브(@wawacoachingcenter) 영상 큐레이션. branch: 지점명(부분일치 접두) → 영상, pools: 주제별 로테이션 풀. 2026-07-13 채널 전수 수집(64개) 기준.",
  "branch": {
    "산본점": { "id": "LlUKrlNNk-g", "title": "군포/산본 학원가 중심의 와와 산본점 소개" },
    "첨단점": { "id": "n7T6Kj_l6uY", "title": "첨단점에서 실력 업그레이드" },
    "율하점": { "id": "ICM22ATK1wk", "title": "1등급의 노하우, 대구 율하동" },
    "부평점": { "id": "zIdwfoMYDus", "title": "인천 부평 와와를 소개합니다" },
    "탄벌점": { "id": "9Rwp_03epac", "title": "광주 탄벌동 와와 졸업생들의 후기" },
    "탄현점": { "id": "CYzul5Y1j_k", "title": "아이들이 자랑하는 일산 탄현 학원" },
    "위례점": { "id": "--3-JgdRK5E", "title": "위례 학생들의 성적은 우리가 책임진다" },
    "평내점": { "id": "uDHYAAmV_uM", "title": "평내동에서 와와를 만나요" },
    "동탄호수점": { "id": "OM1Nk3JpTWw", "title": "동탄호수점을 추천합니다" },
    "주엽점": { "id": "G02-oAafvIw", "title": "일산 주엽 와와 소개" },
    "은평점": { "id": "UIXUaBZdNXU", "title": "은평점에서 시험기간 공부하는 방법" },
    "중동점": { "id": "f97MrCUcrKg", "title": "부천에서 공부하는 비법" },
    "신중동점": { "id": "f97MrCUcrKg", "title": "부천에서 공부하는 비법" },
    "상동점": { "id": "f97MrCUcrKg", "title": "부천에서 공부하는 비법" },
    "옥길점": { "id": "f97MrCUcrKg", "title": "부천에서 공부하는 비법" },
    "옥길스타점": { "id": "f97MrCUcrKg", "title": "부천에서 공부하는 비법" },
    "반달점": { "id": "f97MrCUcrKg", "title": "부천에서 공부하는 비법" },
    "범박점": { "id": "f97MrCUcrKg", "title": "부천에서 공부하는 비법" },
    "비전점": { "id": "hYVFoplgOcU", "title": "평택 와와에서 서울대 합격생이 나온 이유 (합격 인터뷰)" },
    "이충점": { "id": "hYVFoplgOcU", "title": "평택 와와에서 서울대 합격생이 나온 이유 (합격 인터뷰)" }
  },
  "wplus": { "id": "EPg8ZkV9_ZY", "title": "더블유플러스학원 — 수학이 재밌다, 과학이 신난다" },
  "pools": {
    "brand": [
      { "id": "f_skFu40U04", "title": "원장님 인터뷰와 학원 후기" },
      { "id": "LJUzvUn4r1E", "title": "혼자 하기 어려운 공부, 와와는 어때요?" },
      { "id": "V1oYbmHNJWQ", "title": "우리 학원이 좋은 이유" },
      { "id": "ixAQ71YHOAw", "title": "꼼꼼한 관리력이 장점인 학원" },
      { "id": "r_VYgj12xeQ", "title": "맞춤식 교육 방법 소개" },
      { "id": "0rlfgS_d-iE", "title": "2025 소비자가 뽑은 올해의 대상 수상 (교육 부문)" }
    ],
    "school": [
      { "id": "D14y0-jCBlo", "title": "학교별 맞춤 내신의 끝판왕" },
      { "id": "3JPQyEkeJAc", "title": "중간고사는 여기서 준비하세요" },
      { "id": "ixAQ71YHOAw", "title": "꼼꼼한 관리력이 장점인 학원" },
      { "id": "V1oYbmHNJWQ", "title": "우리 학원이 좋은 이유" }
    ],
    "study": [
      { "id": "eZb6FelbjTM", "title": "집중력을 올리는 방법" },
      { "id": "-0i1bQCNzhs", "title": "수행평가를 잘 보는 방법" },
      { "id": "FPzopddBNzQ", "title": "자투리 시간 활용 공부 팁" },
      { "id": "G54iOKUqknw", "title": "겨울방학 플래너 쓰는 법" },
      { "id": "DinSVu9h7RI", "title": "시험기간 벼락치기 팁" },
      { "id": "DuuXgB7iT8s", "title": "새학기를 알차게 준비하자" }
    ],
    "ipsi": [
      { "id": "1QGhXWVo6ug", "title": "왜 수행평가가 중요할까?" },
      { "id": "0Cg7_7zoXeo", "title": "수행평가를 대하는 큰 착각" },
      { "id": "rFL1u0UgmWw", "title": "수행평가 실제사례 — 시험 잘 봐도 A등급이 안 될 수 있다" },
      { "id": "VKgnl4QFSKE", "title": "내신과 수행평가, 두 마리 토끼 잡기" },
      { "id": "04NC6ivL90Y", "title": "생기부에 필수적인 항목 포인트" },
      { "id": "C8heLO8V-lk", "title": "우수 생기부 사례 — 대학과정 탐구" },
      { "id": "IViYyF2WINA", "title": "선택의 폭이 넓어진 교과과정과 대학입학전형" },
      { "id": "09jTqUlFwCQ", "title": "변별력이 없어진 상황, 대학 선발 기준" }
    ],
    "interview": [
      { "id": "hYVFoplgOcU", "title": "영어 5등급의 반전, 평택 와와 서울대 합격생" },
      { "id": "a7zKocCTfUg", "title": "서울대 합격생이 말하는 진짜 공부법" }
    ]
  }
}
